slowstore/__init__.py
slowstore/change.py
slowstore/proxy.py
slowstore/store.py
slowstore/utils.py
slowstore-2.0.4.dist-info/LICENSE
slowstore-2.0.4.dist-info/METADATA
slowstore-2.0.4.dist-info/WHEEL
slowstore-2.0.4.dist-info/RECORD
