Metadata-Version: 2.3
Name: slowstore
Version: 2.0.4
Summary: File json storage backend for your collections
License: MIT
Author: Costa Halicea
Author-email: costa@codechem.com
Requires-Python: >=3.10
Classifier: License :: OSI Approved :: MIT License
Classifier: Programming Language :: Python :: 3
Classifier: Programming Language :: Python :: 3.10
Classifier: Programming Language :: Python :: 3.11
Classifier: Programming Language :: Python :: 3.12
Classifier: Programming Language :: Python :: 3.13
Requires-Dist: pydantic (>=2.8.2,<3.0.0)
Requires-Dist: pytest (>=8.3.4,<9.0.0)
Project-URL: Documentation, https://github.com/42dotmk/slowstore/blob/main/README.md
Project-URL: Homepage, https://github.com/42dotmk/slowstore
Project-URL: Repository, https://github.com/42dotmk/slowstore
